haokjsonapi/__init__.py
haokjsonapi/haokjsonapi.py
haokjsonapi-0.1.1.dist-info/LICENSE
haokjsonapi-0.1.1.dist-info/METADATA
haokjsonapi-0.1.1.dist-info/WHEEL
haokjsonapi-0.1.1.dist-info/RECORD
