Metadata-Version: 2.1
Name: haokjsonapi
Version: 0.1.1
Summary: 
Author: Heather Hao
Author-email: khao@fandm.edu
Requires-Python: >=3.11,<4.0
Classifier: Programming Language :: Python :: 3
Classifier: Programming Language :: Python :: 3.11
